ostd.py
ostd/__init__.py
ostd/__main__.py
ostd/utils.py
ostd-1.0.1.dist-info/DESCRIPTION.rst
ostd-1.0.1.dist-info/METADATA
ostd-1.0.1.dist-info/RECORD
ostd-1.0.1.dist-info/WHEEL
ostd-1.0.1.dist-info/metadata.json
ostd-1.0.1.dist-info/top_level.txt
