Metadata-Version: 2.0
Name: ostd
Version: 1.0.1
Summary: Downloads subtitles from OpenSubtitles
Home-page: https://github.com/Fylipp/ostd
Author: Philipp Ploder
Author-email: UNKNOWN
License: UNKNOWN
Keywords: opensubtitles
Platform: UNKNOWN
Classifier: Development Status :: 3 - Alpha
Classifier: License :: OSI Approved :: MIT License
Classifier: Programming Language :: Python :: 3
Requires-Dist: chardet
